{
  "config": "configs/civil_comments_gemma2_2b.yaml",
  "best_layer": 12,
  "best_accuracy": 0.8633217811584473,
  "layers": {
    "8": {
      "true_label_acc": 0.8610149621963501,
      "spurious_label_acc": 0.8610149621963501
    },
    "9": {
      "true_label_acc": 0.8569780588150024,
      "spurious_label_acc": 0.8569780588150024
    },
    "10": {
      "true_label_acc": 0.861591637134552,
      "spurious_label_acc": 0.861591637134552
    },
    "11": {
      "true_label_acc": 0.8529411554336548,
      "spurious_label_acc": 0.8529411554336548
    },
    "12": {
      "true_label_acc": 0.8633217811584473,
      "spurious_label_acc": 0.8633217811584473
    },
    "13": {
      "true_label_acc": 0.855247974395752,
      "spurious_label_acc": 0.855247974395752
    },
    "14": {
      "true_label_acc": 0.8402537107467651,
      "spurious_label_acc": 0.8402537107467651
    },
    "15": {
      "true_label_acc": 0.8356401324272156,
      "spurious_label_acc": 0.8356401324272156
    },
    "16": {
      "true_label_acc": 0.8241060972213745,
      "spurious_label_acc": 0.8241060972213745
    },
    "17": {
      "true_label_acc": 0.8304498195648193,
      "spurious_label_acc": 0.8304498195648193
    },
    "18": {
      "true_label_acc": 0.8339099884033203,
      "spurious_label_acc": 0.8339099884033203
    },
    "19": {
      "true_label_acc": 0.8408304452896118,
      "spurious_label_acc": 0.8408304452896118
    },
    "20": {
      "true_label_acc": 0.8281430006027222,
      "spurious_label_acc": 0.8281430006027222
    },
    "21": {
      "true_label_acc": 0.8396770358085632,
      "spurious_label_acc": 0.8396770358085632
    },
    "22": {
      "true_label_acc": 0.7895039916038513,
      "spurious_label_acc": 0.7895039916038513
    },
    "23": {
      "true_label_acc": 0.8367934823036194,
      "spurious_label_acc": 0.8367934823036194
    },
    "24": {
      "true_label_acc": 0.7554786205291748,
      "spurious_label_acc": 0.7554786205291748
    },
    "25": {
      "true_label_acc": 0.834486722946167,
      "spurious_label_acc": 0.834486722946167
    }
  }
}